<?xml version="1.0" encoding="UTF-8" ?>
<odoo>
    <data>
        <record id="res_partner_need_receipt" model="ir.ui.view">
            <field name="name">res.partner.form.receipt</field>
            <field name="model">res.partner</field>
            <field name="inherit_id" ref="base.view_partner_form"/>
            <field name="arch" type="xml">
                <xpath expr="//field[@name='customer_stopnum']" position="after">
                    <field name="print_receipt"/>
                </xpath>
            </field>
        </record>

        <record id="sale_order_search_inherit_receipt" model="ir.ui.view">
            <field name="name">sale.order.search.receipt</field>
            <field name="model">sale.order</field>
            <field name="inherit_id" ref="sale.sale_order_view_search_inherit_quotation"/>
            <field name="arch" type="xml">
                <xpath expr="//filter[@name='tomorrow']" position="after">
                    <separator/>
                    <filter string="Need Receipt" name="need_receipt" domain="[('partner_id.print_receipt','=', True)]"/>
                    <separator/>
                </xpath>
            </field>
        </record>
    </data>
</odoo>
